struct2tensor/__init__.py
struct2tensor/calculate.py
struct2tensor/calculate_options.py
struct2tensor/calculate_with_source_paths.py
struct2tensor/create_expression.py
struct2tensor/expression.py
struct2tensor/expression_add.py
struct2tensor/path.py
struct2tensor/prensor.py
struct2tensor/prensor_to_structured_tensor.py
struct2tensor/prensor_util.py
struct2tensor/prensor_value.py
struct2tensor/structured_tensor_to_prensor.py
struct2tensor/version.py
struct2tensor/benchmarks/ops_benchmark.py
struct2tensor/benchmarks/struct2tensor_benchmark.py
struct2tensor/benchmarks/struct2tensor_benchmark_util.py
struct2tensor/expression_impl/__init__.py
struct2tensor/expression_impl/apply_schema.py
struct2tensor/expression_impl/broadcast.py
struct2tensor/expression_impl/depth_limit.py
struct2tensor/expression_impl/filter_expression.py
struct2tensor/expression_impl/index.py
struct2tensor/expression_impl/map_prensor.py
struct2tensor/expression_impl/map_prensor_to_prensor.py
struct2tensor/expression_impl/map_values.py
struct2tensor/expression_impl/parquet.py
struct2tensor/expression_impl/parse_message_level_ex.py
struct2tensor/expression_impl/placeholder.py
struct2tensor/expression_impl/project.py
struct2tensor/expression_impl/promote.py
struct2tensor/expression_impl/promote_and_broadcast.py
struct2tensor/expression_impl/proto.py
struct2tensor/expression_impl/proto_test_util.py
struct2tensor/expression_impl/reroot.py
struct2tensor/expression_impl/size.py
struct2tensor/expression_impl/slice_expression.py
struct2tensor/ops/__init__.py
struct2tensor/ops/_decode_proto_map_op.so
struct2tensor/ops/_decode_proto_sparse_op.so
struct2tensor/ops/_equi_join_any_indices_op.so
struct2tensor/ops/_equi_join_indices_op.so
struct2tensor/ops/_parquet_dataset_op.so
struct2tensor/ops/_run_length_before_op.so
struct2tensor/ops/file_descriptor_set.py
struct2tensor/ops/gen_decode_proto_map_op.py
struct2tensor/ops/gen_decode_proto_sparse.py
struct2tensor/ops/gen_equi_join_any_indices.py
struct2tensor-0.48.0.dist-info/LICENSE
struct2tensor-0.48.0.dist-info/METADATA
struct2tensor-0.48.0.dist-info/WHEEL
struct2tensor-0.48.0.dist-info/top_level.txt
struct2tensor-0.48.0.dist-info/RECORD
