Metadata-Version: 2.2
Name: struct2tensor
Version: 0.48.0
Summary: Struct2Tensor is a package for parsing and manipulating structured data for TensorFlow
Author: Google LLC
Author-email: tensorflow-extended-dev@googlegroups.com
License: Apache 2.0
Keywords: tensorflow protobuf machine learning
Classifier: Development Status :: 4 - Beta
Classifier: Intended Audience :: Developers
Classifier: Intended Audience :: Education
Classifier: Intended Audience :: Science/Research
Classifier: License :: OSI Approved :: Apache Software License
Classifier: Operating System :: MacOS :: MacOS X
Classifier: Operating System :: POSIX :: Linux
Classifier: Programming Language :: Python
Classifier: Programming Language :: Python :: 3.9
Classifier: Programming Language :: Python :: 3.10
Classifier: Programming Language :: Python :: 3.11
Classifier: Programming Language :: Python :: 3 :: Only
Classifier: Topic :: Scientific/Engineering
Classifier: Topic :: Scientific/Engineering :: Artificial Intelligence
Classifier: Topic :: Scientific/Engineering :: Mathematics
Classifier: Topic :: Software Development
Classifier: Topic :: Software Development :: Libraries
Classifier: Topic :: Software Development :: Libraries :: Python Modules
License-File: LICENSE
Requires-Dist: numpy>=1.22
Requires-Dist: protobuf<6.0.0,>=4.25.2; python_version >= "3.11"
Requires-Dist: protobuf<6.0.0,>=4.21.6; python_version < "3.11"
Requires-Dist: tensorflow<2.18,>=2.17
Requires-Dist: tensorflow-metadata<1.18.0,>=1.17.0
Requires-Dist: pyarrow<11,>=10
Dynamic: author
Dynamic: author-email
Dynamic: classifier
Dynamic: description
Dynamic: description-content-type
Dynamic: keywords
Dynamic: license
Dynamic: requires-dist
Dynamic: summary
